pybifrost/__init__.py
pybifrost/analysis_functions.py
pybifrost/mcstas_functions.py
pybifrost/neutron_functions.py
pybifrost/constants/Es_fit.npy
pybifrost/constants/Es_gauss.npy
pybifrost/constants/Es_std.npy
pybifrost/constants/LAD.npy
pybifrost/constants/LSA.npy
pybifrost/constants/dL.npy
pybifrost/constants/dphi.npy
pybifrost/constants/widths.npy
pybifrost-1.0.27.dist-info/METADATA
pybifrost-1.0.27.dist-info/WHEEL
pybifrost-1.0.27.dist-info/licenses/LICENSE
pybifrost-1.0.27.dist-info/RECORD
