Metadata-Version: 2.4
Name: pybifrost
Version: 1.0.27
Summary: A package for analysis of BIFROST simulation data and resolution functions
Project-URL: Homepage, https://github.com/nicolai3008/pyneutron-bifrost
Project-URL: Issues, https://github.com/nicolai3008/pyneutron-bifrost/issues
Author-email: Nicolai Amin <nicolaiamin1@gmail.com>
License-Expression: MIT
License-File: LICENSE
Requires-Python: >=3.8
Requires-Dist: matplotlib==3.7.2
Requires-Dist: numpy==1.24.3
Requires-Dist: pandas==2.0.3
Requires-Dist: scipy==1.11.4
Requires-Dist: seaborn==0.13.2
Requires-Dist: tqdm==4.65.0
